mesmer_openscmrunner/__init__.py
mesmer_openscmrunner/draw_realisations/__init__.py
mesmer_openscmrunner-2.0.1.dist-info/AUTHORS
mesmer_openscmrunner-2.0.1.dist-info/LICENSE
mesmer_openscmrunner-2.0.1.dist-info/METADATA
mesmer_openscmrunner-2.0.1.dist-info/WHEEL
mesmer_openscmrunner-2.0.1.dist-info/top_level.txt
mesmer_openscmrunner-2.0.1.dist-info/RECORD
