Metadata-Version: 2.1
Name: mesmer-openscmrunner
Version: 2.0.1
Summary: Coupling between MESMER and OpenSCM-Runner
Home-page: https://github.com/MESMER-group/mesmer-openscmrunner
Author: Zeb Nicholls, Lea Beusch, Mathias Hauser, Jared Lewis
Author-email: zebedee.nicholls@climate-energy-college.org, lea.beusch@env.ethz.ch, mathias.hauser@env.ethz.ch, jared.lewis@climate-energy-college.org
License: GPLv3+
Project-URL: Bug Reports, https://github.com/MESMER-group/mesmer-openscmrunner/issues
Project-URL: Source, https://github.com/MESMER-group/mesmer-openscmrunner
Keywords: MESMER,netCDF,python,climate,atmosphere,simple climate model,reduced complexity climate model,emulation,earth system model emulation
Platform: UNKNOWN
Classifier: Development Status :: 4 - Beta
Classifier: License :: OSI Approved :: GNU General Public License v3 or later (GPLv3+)
Classifier: Intended Audience :: Developers
Classifier: Operating System :: OS Independent
Classifier: Intended Audience :: Science/Research
Classifier: Programming Language :: Python
Classifier: Programming Language :: Python :: 3
Classifier: Programming Language :: Python :: 3.7
Classifier: Programming Language :: Python :: 3.8
Classifier: Programming Language :: Python :: 3.9
Classifier: Topic :: Scientific/Engineering
Requires-Python: >=3.7
Requires-Dist: mesmer-emulator
Requires-Dist: openscm-runner (>=0.6)
Requires-Dist: scmdata
Requires-Dist: xarray
Requires-Dist: importlib-metadata ; python_version < "3.8"
Provides-Extra: dev
Requires-Dist: bandit ; extra == 'dev'
Requires-Dist: black ; extra == 'dev'
Requires-Dist: black-nb ; extra == 'dev'
Requires-Dist: flake8 ; extra == 'dev'
Requires-Dist: isort ; extra == 'dev'
Requires-Dist: mypy ; extra == 'dev'
Requires-Dist: nbdime ; extra == 'dev'
Requires-Dist: openscm-zenodo ; extra == 'dev'
Requires-Dist: pydocstyle ; extra == 'dev'
Requires-Dist: pylint ; extra == 'dev'
Requires-Dist: twine ; extra == 'dev'
Requires-Dist: ipython ; extra == 'dev'
Requires-Dist: nbsphinx ; extra == 'dev'
Requires-Dist: numpydoc ; extra == 'dev'
Requires-Dist: sphinx ; extra == 'dev'
Requires-Dist: sphinx-book-theme ; extra == 'dev'
Requires-Dist: sphinx-copybutton ; extra == 'dev'
Requires-Dist: codecov ; extra == 'dev'
Requires-Dist: nbval ; extra == 'dev'
Requires-Dist: pytest ; extra == 'dev'
Requires-Dist: pytest-cov ; extra == 'dev'
Requires-Dist: pytest-xdist ; extra == 'dev'
Provides-Extra: docs
Requires-Dist: ipython ; extra == 'docs'
Requires-Dist: nbsphinx ; extra == 'docs'
Requires-Dist: numpydoc ; extra == 'docs'
Requires-Dist: sphinx ; extra == 'docs'
Requires-Dist: sphinx-book-theme ; extra == 'docs'
Requires-Dist: sphinx-copybutton ; extra == 'docs'
Provides-Extra: tests
Requires-Dist: codecov ; extra == 'tests'
Requires-Dist: nbval ; extra == 'tests'
Requires-Dist: pytest ; extra == 'tests'
Requires-Dist: pytest-cov ; extra == 'tests'
Requires-Dist: pytest-xdist ; extra == 'tests'
